CHE_QNM/HeunCfile.py
CHE_QNM/__init__.py
CHE_QNM/data/A_32_l2_m2_n0.txt
CHE_QNM/data/A_32_l2_m2_n1.txt
CHE_QNM/data/A_32_l2_m2_n2.txt
CHE_QNM/data/coefficients_n0.txt
CHE_QNM/data/coefficients_n1.txt
CHE_QNM/data/coefficients_n10.txt
CHE_QNM/data/coefficients_n11.txt
CHE_QNM/data/coefficients_n12.txt
CHE_QNM/data/coefficients_n13.txt
CHE_QNM/data/coefficients_n14.txt
CHE_QNM/data/coefficients_n15.txt
CHE_QNM/data/coefficients_n16.txt
CHE_QNM/data/coefficients_n17.txt
CHE_QNM/data/coefficients_n18.txt
CHE_QNM/data/coefficients_n19.txt
CHE_QNM/data/coefficients_n2.txt
CHE_QNM/data/coefficients_n20.txt
CHE_QNM/data/coefficients_n21.txt
CHE_QNM/data/coefficients_n22.txt
CHE_QNM/data/coefficients_n23.txt
CHE_QNM/data/coefficients_n24.txt
CHE_QNM/data/coefficients_n25.txt
CHE_QNM/data/coefficients_n26.txt
CHE_QNM/data/coefficients_n27.txt
CHE_QNM/data/coefficients_n28.txt
CHE_QNM/data/coefficients_n29.txt
CHE_QNM/data/coefficients_n3.txt
CHE_QNM/data/coefficients_n30.txt
CHE_QNM/data/coefficients_n31.txt
CHE_QNM/data/coefficients_n32.txt
CHE_QNM/data/coefficients_n33.txt
CHE_QNM/data/coefficients_n34.txt
CHE_QNM/data/coefficients_n35.txt
CHE_QNM/data/coefficients_n36.txt
CHE_QNM/data/coefficients_n37.txt
CHE_QNM/data/coefficients_n38.txt
CHE_QNM/data/coefficients_n39.txt
CHE_QNM/data/coefficients_n4.txt
CHE_QNM/data/coefficients_n40.txt
CHE_QNM/data/coefficients_n41.txt
CHE_QNM/data/coefficients_n5.txt
CHE_QNM/data/coefficients_n6.txt
CHE_QNM/data/coefficients_n7.txt
CHE_QNM/data/coefficients_n8.txt
CHE_QNM/data/coefficients_n9.txt
CHE_QNM/data/qnm_32_l2_m2_n0.txt
CHE_QNM/data/qnm_32_l2_m2_n1.txt
CHE_QNM/data/qnm_32_l2_m2_n2.txt
CHE_QNM/data/qnm_frequencies.txt
CHE_QNM/data/qnm_rough_l2_m-1_n0.txt
CHE_QNM/data/qnm_rough_l2_m-1_n1.txt
CHE_QNM/data/qnm_rough_l2_m-1_n2.txt
CHE_QNM/data/qnm_rough_l2_m-2_n0.txt
CHE_QNM/data/qnm_rough_l2_m-2_n1.txt
CHE_QNM/data/qnm_rough_l2_m-2_n2.txt
CHE_QNM/data/qnm_rough_l2_m0_n0.txt
CHE_QNM/data/qnm_rough_l2_m0_n1.txt
che_qnm-0.0.6.dist-info/licenses/LICENSE.txt
che_qnm-0.0.6.dist-info/METADATA
che_qnm-0.0.6.dist-info/WHEEL
che_qnm-0.0.6.dist-info/top_level.txt
che_qnm-0.0.6.dist-info/RECORD
