Metadata-Version: 2.4
Name: CHE_QNM
Version: 0.0.6
Summary: Package to solve QNMs using HeunC_functions
Author-email: "Stef J.B. Husken" <stef.husken@student.kuleuven.be>
License-Expression: MIT
Classifier: Programming Language :: Python :: 3
Classifier: Operating System :: OS Independent
Requires-Python: >=3.9
License-File: LICENSE.txt
Dynamic: license-file
